squema.py
squema-0.0.1.dist-info/LICENSE
squema-0.0.1.dist-info/METADATA
squema-0.0.1.dist-info/WHEEL
squema-0.0.1.dist-info/top_level.txt
squema-0.0.1.dist-info/RECORD
