Metadata-Version: 2.1
Name: squema
Version: 0.0.1
Summary: Smarter data structures
Home-page: https://github.com/Funk66/squema
Author: Guillermo Guirao Aguilar
Author-email: contact@guillermoguiraoaguilar.com
License: MIT
Platform: UNKNOWN
Classifier: Programming Language :: Python :: 3.7
